FacebookDownloader/FacebookVideoDownloader.py
FacebookDownloader/__init__.py
FVD-1.0.6.dist-info/METADATA
FVD-1.0.6.dist-info/WHEEL
FVD-1.0.6.dist-info/top_level.txt
FVD-1.0.6.dist-info/RECORD
