Metadata-Version: 2.1
Name: FVD
Version: 1.0.6
Summary: Facebook Video Downloading via Python Package
Author: Razi Ahmed Iqbal
Author-email: <raziahmediqbal@gmail.com>
Keywords: python,facebook,video,downloader,facebook video downloader,downlaod facebook videos
Requires-Dist: beautifulsoup4
Requires-Dist: selenium
